Workbook

Sheet Comapany Value
B2: Amount in Crores
B3: Comparable Company Valuation
D5: Market Data | J5: Financials | N5: Valuation
B6: Company | C6: Ticker | D6: Share Price | E6: Share Outstanding | F6: Equity Value | G6: Net Debt | H6: Enterprise Value | J6: Revenue | K6: EBITDA | L6: Net Income | N6: EV/Revenue | O6: EV/EBITDA | P6: P/E
B8: =Data!C3 -> Infosys | C8: INFY | D8: =Data!D3 -> 1280.05 | E8: =Data!E3 -> 405.54 | F8: =D8*E8 -> 519111.48 | G8: =Data!I3 -> -15659 | H8: =F8+G8 -> 503452.48 | J8: =Data!K3 -> 173173 | K8: =Data!L3 -> 45339 | L8: =Data!M3 -> 28003 | N8: =$H8/J8 -> 2.9072227 | O8: =$H8/K8 -> 11.104181 | P8: =F8/L8 -> 18.537709
B9: =Data!C4 -> TCS | C9: TCS | D9: =Data!D4 -> 2478.95 | E9: =Data!E4 -> 361.81 | F9: =D9*E9 -> 896908.9 | G9: =Data!I4 -> -4531 | H9: =F9+G9 -> 892377.9 | J9: =Data!K4 -> 260802 | K9: =Data!L4 -> 74775 | L9: =Data!M4 -> 47963 | N9: =$H9/J9 -> 3.4216682 | O9: =$H9/K9 -> 11.934175 | P9: =F9/L9 -> 18.700017
B10: =Data!C5 -> HCL Technologies | C10: WIPRO | D10: =Data!D5 -> 1356.95 | E10: =Data!E5 -> 271.37 | F10: =D10*E10 -> 368235.52 | G10: =Data!I5 -> -14509 | H10: =F10+G10 -> 353726.52 | J10: =Data!K5 -> 126409 | K10: =Data!L5 -> 28179 | L10: =Data!M5 -> 16471 | N10: =$H10/J10 -> 2.7982701 | O10: =$H10/K10 -> 12.552842 | P10: =F10/L10 -> 22.356598
B11: =Data!C6 -> Wipro | C11: HCLTECH | D11: =Data!D6 -> 203.6 | E11: =Data!E6 -> 1048.8 | F11: =D11*E11 -> 213535.68 | G11: =Data!I6 -> 3966.3 | H11: =F11+G11 -> 217501.98 | J11: =Data!K6 -> 90891.9 | K11: =Data!L6 -> 21785.8 | L11: =Data!M6 -> 13332 | N11: =$H11/J11 -> 2.3929743 | O11: =$H11/K11 -> 9.9836582 | P11: =F11/L11 -> 16.016778
B12: =Data!C7 -> Tech Mahindra | C12: TECHHM | D12: =Data!D7 -> 1345.4 | E12: =Data!E7 -> 97.98 | F12: =D12*E12 -> 131822.29 | G12: =Data!I7 -> -2587.8 | H12: =F12+G12 -> 129234.49 | J12: =Data!K7 -> 55123.3 | K12: =Data!L7 -> 8715.6 | L12: =Data!M7 -> 4591 | N12: =$H12/J12 -> 2.3444622 | O12: =$H12/K12 -> 14.827951 | P12: =F12/L12 -> 28.713198
B14: High | N14: =MAX(N8:N12) -> 3.4216682 | O14: =MAX(O8:O12) -> 14.827951 | P14: =MAX(P8:P12) -> 28.713198
B15: 75th Percentile | N15: =QUARTILE(N8:N12,3) -> 2.9072227 | O15: =QUARTILE(O8:O12,3) -> 12.552842 | P15: =QUARTILE(P8:P12,3) -> 22.356598
B16: Average | N16: =AVERAGE(N8:N12) -> 2.7729195 | O16: =AVERAGE(O8:O12) -> 12.080561 | P16: =AVERAGE(P8:P12) -> 20.86486
B17: Median | N17: =MEDIAN(N8:N12) -> 2.7982701 | O17: =MEDIAN(O8:O12) -> 11.934175 | P17: =MEDIAN(P8:P12) -> 18.700017
B18: 25th Percentile | N18: =QUARTILE(N8:N12,1) -> 2.3929743 | O18: =QUARTILE(O8:O12,1) -> 11.104181 | P18: =QUARTILE(P8:P12,1) -> 18.537709
B19: Low | N19: =MIN(N8:N12) -> 2.3444622 | O19: =MIN(O8:O12) -> 9.9836582 | P19: =MIN(P8:P12) -> 16.016778
B21: Infosys Comparable Valuation | N21: EV/Revenue | O21: EV/EBITDA | P21: P/E
B23: Implied Enterprise Value | N23: =N17*J8 -> 484584.82 | O23: =O17*K8 -> 541083.54 | P23: =+P25+P24 -> 507997.57
B24: Net Debt | N24: =$G$8 -> -15659 | O24: =$G$8 -> -15659 | P24: =$G$8 -> -15659
B25: Implied Market Value | N25: =N23-N24 -> 500243.82 | O25: =O23-O24 -> 556742.54 | P25: =P17*L8 -> 523656.57
B26: Share Outstanding | N26: =$E$8 -> 405.54 | O26: =$E$8 -> 405.54 | P26: =$E$8 -> 405.54
B28: Implied Value Per Share | N28: =N25/N26 -> 1233.5252 | O28: =O25/O26 -> 1372.8425 | P28: =P25/P26 -> 1291.2575
B30: Source: Screener.in | N30: =IF(N28>$D$8,"Undervalued","Overvalued") -> Overvalued | O30: =IF(O28>$D$8,"Undervalued","Overvalued") -> Undervalued | P30: =IF(P28>$D$8,"Undervalued","Overvalued") -> Undervalued

Sheet Data
B2: S.No. | C2: Name | D2: CMP Rs. | E2: No. Eq. Shares Cr. | F2: Market Capitalization | G2: Debt Rs.Cr. | H2: Cash End Rs.Cr. | I2: Net Debt | J2: EV | K2: Sales Rs.Cr. | L2: EBITDA | M2: NP 12M Rs.Cr. | N2: EBIT 12M Rs.Cr. | O2: Dep 12M Rs.Cr.
B3: 1 | C3: Infosys | D3: 1280.05 | E3: 405.54 | F3: =E3*D3 -> 519111.48 | G3: 8796 | H3: 24455 | I3: =G3-H3 -> -15659 | J3: =F3+G3-H3 -> 503452.48 | K3: 173173 | L3: =N3+O3 -> 45339 | M3: 28003 | N3: 40563 | O3: 4776
B4: 2 | C4: TCS | D4: 2478.95 | E4: 361.81 | F4: =E4*D4 -> 896908.9 | G4: 10932 | H4: 15463 | I4: =G4-H4 -> -4531 | J4: =F4+G4-H4 -> 892377.9 | K4: 260802 | L4: =N4+O4 -> 74775 | M4: 47963 | N4: 69242 | O4: 5533
B5: 3 | C5: HCL Technologies | D5: 1356.95 | E5: 271.37 | F5: =E5*D5 -> 368235.52 | G5: 6780 | H5: 21289 | I5: =G5-H5 -> -14509 | J5: =F5+G5-H5 -> 353726.52 | K5: 126409 | L5: =N5+O5 -> 28179 | M5: 16471 | N5: 23876 | O5: 4303
B6: 4 | C6: Wipro | D6: 203.6 | E6: 1048.8 | F6: =E6*D6 -> 213535.68 | G6: 16163.7 | H6: 12197.4 | I6: =G6-H6 -> 3966.3 | J6: =F6+G6-H6 -> 217501.98 | K6: 90891.9 | L6: =N6+O6 -> 21785.8 | M6: 13332 | N6: 18881.9 | O6: 2903.9
B7: 5 | C7: Tech Mahindra | D7: 1345.4 | E7: 97.98 | F7: =E7*D7 -> 131822.29 | G7: 1954.4 | H7: 4542.2 | I7: =G7-H7 -> -2587.8 | J7: =F7+G7-H7 -> 129234.49 | K7: 55123.3 | L7: =N7+O7 -> 8715.6 | M7: 4591 | N7: 6853 | O7: 1862.6

Sheet Football Analysis
B2: Football Field Analysis - Data
C3: OpenLow | D3: Low | E3: OpenHigh | F3: High
B4: Comps | C4: 510.33 | D4: 510.33 | E4: 780.21 | F4: 780.21
B5: DCF Bear | C5: 759.73 | D5: 759.73 | E5: 936.88 | F5: 936.88
B6: DCF Base | C6: 924.13 | D6: 924.13 | E6: 1315.28 | F6: 1315.28
B7: DCF Bull | C7: 1091.88 | D7: 1091.88 | E7: 1866.9 | F7: 1866.9
B8: 52week High/Low | C8: 1264.1 | D8: 1264.1 | E8: 1728 | F8: 1728
